fiftyone_pipeline_cloudrequestengine/__init__.py
fiftyone_pipeline_cloudrequestengine/clouddata.py
fiftyone_pipeline_cloudrequestengine/cloudengine.py
fiftyone_pipeline_cloudrequestengine/cloudrequestengine.py
fiftyone_pipeline_cloudrequestengine/cloudrequestexception.py
fiftyone_pipeline_cloudrequestengine/constants.py
fiftyone_pipeline_cloudrequestengine/requestclient.py
fiftyone_pipeline_cloudrequestengine-4.5.3.dist-info/METADATA
fiftyone_pipeline_cloudrequestengine-4.5.3.dist-info/WHEEL
fiftyone_pipeline_cloudrequestengine-4.5.3.dist-info/top_level.txt
fiftyone_pipeline_cloudrequestengine-4.5.3.dist-info/RECORD
