Metadata-Version: 2.4
Name: fiftyone_pipeline_cloudrequestengine
Version: 4.5.3
Summary: This package contains a shared engine that is used to make requests to the 51Degrees cloud service on behalf of other data services such as device detection or location.
Home-page: https://51degrees.com/
Author: 51Degrees Engineering
Author-email: engineering@51degrees.com
License: EUPL-1.2
Classifier: Development Status :: 5 - Production/Stable
Classifier: Programming Language :: Python
Classifier: License :: OSI Approved :: European Union Public Licence 1.2 (EUPL 1.2)
Classifier: Operating System :: OS Independent
Classifier: Topic :: Software Development :: Libraries :: Python Modules
Requires-Python: >=3.8
Requires-Dist: fiftyone_pipeline_engines
Requires-Dist: requests
Dynamic: author
Dynamic: author-email
Dynamic: classifier
Dynamic: description
Dynamic: description-content-type
Dynamic: home-page
Dynamic: license
Dynamic: requires-dist
Dynamic: requires-python
Dynamic: summary
